newbuscard/__init__.py
newbuscard/buscardm.png
newbuscard/main.py
newbuscard-0.2.0.dist-info/METADATA
newbuscard-0.2.0.dist-info/WHEEL
newbuscard-0.2.0.dist-info/top_level.txt
newbuscard-0.2.0.dist-info/RECORD
