Metadata-Version: 2.4
Name: newbuscard
Version: 0.2.0
Summary: A Business Card Management App built with CustomTkinter
Author-email: Jongwhan Kang <hotjwk@email.com>
License-Expression: MIT
Requires-Python: >=3.12
Requires-Dist: customtkinter>=5.2.2
Requires-Dist: pillow>=11.2.1
Requires-Dist: python-decouple>=3.8
